oref/__init__.py
oref/alerts.py
oref/config.py
oref/loader.py
oref/types.py
oref-0.2.0.dist-info/licenses/LICENSE
oref-0.2.0.dist-info/METADATA
oref-0.2.0.dist-info/WHEEL
oref-0.2.0.dist-info/top_level.txt
oref-0.2.0.dist-info/RECORD
