Metadata-Version: 2.4
Name: oref
Version: 0.2.0
Summary: Unofficial API for the Israeli Home Front Command
Home-page: https://github.com/emrothenberg/oref
Author: emrothenberg
License: MIT
Keywords: oref,homefront,home front,pikud,haoref,rockets,missiles,tzeva adom,emergency,api,idf,israel,israeli,alerts,red alert,sirens,civil defense,air raid,public safety,realtime,defense,national alert,region alerts,security
Classifier: Development Status :: 3 - Alpha
Classifier: Intended Audience :: Developers
Classifier: License :: OSI Approved :: MIT License
Classifier: Programming Language :: Python :: 3.11
License-File: LICENSE
Requires-Dist: requests>=2.31
Dynamic: author
Dynamic: classifier
Dynamic: description
Dynamic: description-content-type
Dynamic: home-page
Dynamic: keywords
Dynamic: license
Dynamic: license-file
Dynamic: requires-dist
Dynamic: summary
